splurge_tabular/__init__.py
splurge_tabular/common_utils.py
splurge_tabular/error_codes.py
splurge_tabular/exceptions.py
splurge_tabular/protocols.py
splurge_tabular/streaming_tabular_data_model.py
splurge_tabular/tabular_data_model.py
splurge_tabular/tabular_utils.py
splurge_tabular-2025.1.0.dist-info/licenses/LICENSE
splurge_tabular-2025.1.0.dist-info/METADATA
splurge_tabular-2025.1.0.dist-info/WHEEL
splurge_tabular-2025.1.0.dist-info/top_level.txt
splurge_tabular-2025.1.0.dist-info/RECORD
