Metadata-Version: 2.4
Name: splurge-tabular
Version: 2025.1.0
Summary: A Python library for tabular data processing with in-memory and streaming support
Author: Jim Schilling
Maintainer: Jim Schilling
License-Expression: MIT
Project-URL: Homepage, https://github.com/jim-schilling/splurge-tabular
Project-URL: Repository, https://github.com/jim-schilling/splurge-tabular
Project-URL: Issues, https://github.com/jim-schilling/splurge-tabular/issues
Project-URL: Changelog, https://github.com/jim-schilling/splurge-tabular/blob/main/CHANGELOG.md
Keywords: tabular,data,csv,dsv,delimited,processing,streaming
Classifier: Development Status :: 3 - Alpha
Classifier: Intended Audience :: Developers
Classifier: Operating System :: OS Independent
Classifier: Programming Language :: Python :: 3
Classifier: Programming Language :: Python :: 3.10
Classifier: Programming Language :: Python :: 3.11
Classifier: Programming Language :: Python :: 3.12
Classifier: Programming Language :: Python :: 3.13
Classifier: Topic :: Software Development :: Libraries :: Python Modules
Classifier: Topic :: Scientific/Engineering :: Information Analysis
Requires-Python: >=3.10
License-File: LICENSE
Requires-Dist: splurge-typer>=2025.1.0
Provides-Extra: dev
Requires-Dist: pytest>=7.0.0; extra == "dev"
Requires-Dist: pytest-cov>=4.0.0; extra == "dev"
Requires-Dist: pytest-xdist>=3.0.0; extra == "dev"
Requires-Dist: ruff>=0.1.0; extra == "dev"
Requires-Dist: mypy>=1.0.0; extra == "dev"
Requires-Dist: pytest-mock>=3.0.0; extra == "dev"
Requires-Dist: pre-commit>=3.0.0; extra == "dev"
Requires-Dist: hypothesis>=6.0.0; extra == "dev"
Provides-Extra: cli
Requires-Dist: typer>=0.9.0; extra == "cli"
Requires-Dist: rich>=13.0.0; extra == "cli"
Dynamic: license-file
